MANIFEST.in
README.rst
setup.py
docs/CONTRIBUTORS.txt
docs/HISTORY.txt
docs/LICENSE.GPL
docs/LICENSE.txt
docs/_build/html/_sources/contributing.rst.txt
docs/_build/html/_sources/index.rst.txt
docs/_build/html/_sources/installing.rst.txt
docs/_build/html/_sources/quickstart.rst.txt
docs/_build/html/_sources/reference_guide.rst.txt
docs/_build/html/_sources/usage_guide.rst.txt
fastkml/__init__.py
fastkml/atom.py
fastkml/base.py
fastkml/config.py
fastkml/geometry.py
fastkml/gx.py
fastkml/kml.py
fastkml/styles.py
fastkml/test_main.py
fastkml_klinden.egg-info/PKG-INFO
fastkml_klinden.egg-info/SOURCES.txt
fastkml_klinden.egg-info/dependency_links.txt
fastkml_klinden.egg-info/entry_points.txt
fastkml_klinden.egg-info/not-zip-safe
fastkml_klinden.egg-info/requires.txt
fastkml_klinden.egg-info/top_level.txt