Metadata-Version: 1.1
Name: fastkml-klinden
Version: 0.11
Summary: Fast KML processing in python (forked from https://github.com/cleder/fastkml)
Home-page: https://github.com/klinden/fastkml
Author: Kyle Linden
Author-email: linden.kyle@gmail.com
License: LGPL
Keywords: GIS KML Google Maps OpenLayers
Platform: UNKNOWN
Classifier: Topic :: Scientific/Engineering :: GIS
Classifier: Programming Language :: Python
Classifier: Programming Language :: Python :: 2
Classifier: Programming Language :: Python :: 2.6
Classifier: Programming Language :: Python :: 2.7
Classifier: Programming Language :: Python :: 3
Classifier: Programming Language :: Python :: 3.2
Classifier: Programming Language :: Python :: 3.3
Classifier: Programming Language :: Python :: 3.4
Classifier: Intended Audience :: Developers
Classifier: License :: OSI Approved :: GNU Library or Lesser General Public License (LGPL)
Classifier: Development Status :: 5 - Production/Stable
Classifier: Operating System :: OS Independent
